wot/__init__.py
wot/__main__.py
wot/dataset_util.py
wot/gene_set_scores.py
wot/population.py
wot/commands/__init__.py
wot/commands/cells_by_gene_set.py
wot/commands/census.py
wot/commands/convert_matrix.py
wot/commands/diff_exp.py
wot/commands/fates.py
wot/commands/gene_set_scores.py
wot/commands/optimal_transport.py
wot/commands/optimal_transport_validation.py
wot/commands/trajectory.py
wot/commands/trajectory_divergence.py
wot/commands/trajectory_trends.py
wot/commands/transition_table.py
wot/commands/util.py
wot/graphics/__init__.py
wot/graphics/color.py
wot/graphics/plot.py
wot/io/__init__.py
wot/io/io.py
wot/io/performance.py
wot/ot/__init__.py
wot/ot/initializer.py
wot/ot/optimal_transport.py
wot/ot/optimal_transport_validation.py
wot/ot/ot_model.py
wot/ot/util.py
wot/simulate/__init__.py
wot/simulate/simulate.py
wot/tmap/__init__.py
wot/tmap/chaining.py
wot/tmap/diff_exp.py
wot/tmap/trajectory_divergence.py
wot/tmap/transport_map_model.py
wot/tmap/util.py
wot-1.0.8.post2.dist-info/LICENSE
wot-1.0.8.post2.dist-info/METADATA
wot-1.0.8.post2.dist-info/WHEEL
wot-1.0.8.post2.dist-info/entry_points.txt
wot-1.0.8.post2.dist-info/top_level.txt
wot-1.0.8.post2.dist-info/RECORD
